LICENSE
MANIFEST.in
README.rst
setup.py
spotinst_agent/__init__.py
spotinst_agent/agent.py
spotinst_agent/agentinit.py
spotinst_agent/basemodule.py
spotinst_agent/scheduler.py
spotinst_agent/taskmanager.py
spotinst_agent/utils.py
spotinst_agent/data/configuration/basemodule.yml
spotinst_agent/data/configuration/spotinst-agent.yml
spotinst_agent/data/installation/agent-init.sh
spotinst_agent_2_beta.egg-info/PKG-INFO
spotinst_agent_2_beta.egg-info/SOURCES.txt
spotinst_agent_2_beta.egg-info/dependency_links.txt
spotinst_agent_2_beta.egg-info/entry_points.txt
spotinst_agent_2_beta.egg-info/requires.txt
spotinst_agent_2_beta.egg-info/top_level.txt